{
      "Aperture-with-Max-Focal-Length": {
            "f/4-5.6-IS-II": [
                  "1001"
            ],
            "f/1.8-G": [
                  "1002"
            ],
            "f/1.8-STM": [
                  "1003"
            ],
            "f/3.5-5.6G-ED-VR": [
                  "1004"
            ],
            "f/3.5-5.6G": [
                  "1005"
            ],
            "f/1.8": [
                  "1007",
                  "1008"
            ],
            "F/3.5-6.3": [
                  "1009"
            ],
            "f/4-L-USM": [
                  "1010"
            ]
      },
      "Aperture-with-Min-Focal-Length": {
            "f/22---32": [
                  "1001"
            ],
            "f/16": [
                  "1002"
            ],
            "f/3.5": [
                  "1004"
            ],
            "f/22": [
                  "1005",
                  "1006",
                  "1010"
            ]
      },
      "Canon": [
            "1001",
            "1003",
            "1010"
      ],
      "Black": [
            "1001",
            "1002",
            "1003",
            "1004",
            "1005",
            "1006",
            "1007",
            "1008",
            "1009",
            "1010"
      ],
      "Canon-DSLRs": [
            "1001",
            "1003"
      ],
      "Dimensions": {
            "70-x-108-mm-(Diameter-x-Length)": [
                  "1001"
            ],
            "72-x-52.5-mm-(Diameter-x-Length)": [
                  "1002"
            ],
            "72-x-85-mm-(Diameter-x-Length)": [
                  "1005"
            ],
            "78.1-x-99-mm-(Diameter-x-Length)": [
                  "1006"
            ]
      },
      "MM": [
            "1001"
      ],
      "Filter-Attachment-Size": {
            "58-mm": [
                  "1001",
                  "1002"
            ],
            "49-mm": [
                  "1003"
            ],
            "67-mm": [
                  "1004",
                  "1005",
                  "1006",
                  "1007",
                  "1009"
            ],
            "77-mm": [
                  "1010"
            ]
      },
      "Canon-Mount": [
            "1001",
            "1006",
            "1008",
            "1009"
      ],
      "Telephoto": [
            "1001",
            "1007",
            "1009"
      ],
      "Maximum-Focal-Length": {
            "250-mm": [
                  "1001"
            ],
            "50-mm": [
                  "1002",
                  "1003"
            ],
            "140-mm": [
                  "1004"
            ],
            "85-mm": [
                  "1005"
            ],
            "300-mm": [
                  "1006",
                  "1009"
            ],
            "45-mm": [
                  "1007",
                  "1008"
            ],
            "40-mm": [
                  "1010"
            ]
      },
      "Maximum-Magnification-(x)": {
            "0.31": [
                  "1001"
            ],
            "0.21x": [
                  "1003"
            ],
            "0.23-x": [
                  "1004"
            ],
            "1:3": [
                  "1006"
            ],
            "0.3": [
                  "1007",
                  "1009"
            ],
            "0.24": [
                  "1010"
            ]
      },
      "Minimum-Aperture": {
            "22---32": [
                  "1001"
            ],
            "F/22": [
                  "1003"
            ],
            "22": [
                  "1006",
                  "1010"
            ],
            "F/16": [
                  "1007"
            ],
            "F/22---40": [
                  "1009"
            ]
      },
      "Minimum-Focal-Length": {
            "55-mm": [
                  "1001"
            ],
            "18-mm": [
                  "1004"
            ],
            "16-mm": [
                  "1005"
            ],
            "28-mm": [
                  "1006",
                  "1009"
            ],
            "45-mm": [
                  "1007"
            ],
            "1.8": [
                  "1008"
            ],
            "17-mm": [
                  "1010"
            ]
      },
      "Model": {
            "EF-S-55---250-mm-f/4-5.6-IS-II": [
                  "1001"
            ],
            "AF-S-NIKKOR-50mm-f/1.8G-Lens": [
                  "1002"
            ],
            "EF-50-mm-f/1.8-STM": [
                  "1003"
            ],
            "F013N": [
                  "1007"
            ],
            "SP-45mm-Lens": [
                  "1008"
            ],
            "A010E-Lens\u00ef\u00bf\u00bd": [
                  "1009"
            ],
            "EF-17---40-mm-f/4L-USM": [
                  "1010"
            ]
      },
      "Telephoto-Zoom": [
            "1001",
            "1001",
            "1005",
            "1005"
      ],
      "Zoom": [
            "1001",
            "1004",
            "1004",
            "1005",
            "1006",
            "1009",
            "1010",
            "1010"
      ],
      "Sales-Package": {
            "Lens": [
                  "1001",
                  "1004",
                  "1010"
            ],
            "EF-50-mm-f/1.8-STM-Lens": [
                  "1003"
            ],
            "Lens,-Lens-Hood": [
                  "1006"
            ],
            "1-Lens,-Mount-Cap,-Owners-Manual": [
                  "1007",
                  "1009"
            ],
            "Lense-&-Manual": [
                  "1008"
            ]
      },
      "Wildlife": [
            "1001"
      ],
      "Warranty": {
            "2-Years": [
                  "1001",
                  "1002",
                  "1003",
                  "1005",
                  "1010"
            ],
            "4": [
                  "1006"
            ],
            "2": [
                  "1007",
                  "1008",
                  "1009"
            ]
      },
      "Weight": {
            "0.345-kg": [
                  "1001"
            ],
            "610-g": [
                  "1002"
            ],
            "0.202-kg": [
                  "1003"
            ],
            "450-g": [
                  "1004"
            ],
            "480-g": [
                  "1005",
                  "1006"
            ],
            "515-g": [
                  "1007"
            ],
            "513-g": [
                  "1008"
            ],
            "250-g": [
                  "1009"
            ],
            "475-g": [
                  "1010"
            ]
      },
      "Nikon": [
            "1002",
            "1004",
            "1005"
      ],
      "Nikon-DSLRs": [
            "1002",
            "1005"
      ],
      "Lens-Cap": {
            "Snap-on": [
                  "1002",
                  "1005"
            ],
            "Yes": [
                  "1003"
            ]
      },
      "Lens-Case": {
            "CL-1013": [
                  "1002"
            ],
            "No": [
                  "1003"
            ],
            "CL-1015": [
                  "1005"
            ]
      },
      "FX": [
            "1002"
      ],
      "Lens-Hood": {
            "HB-47": [
                  "1002"
            ],
            "No": [
                  "1003"
            ],
            "HB-39": [
                  "1005"
            ]
      },
      "AF-S": [
            "1002",
            "1004",
            "1005"
      ],
      "Standard": [
            "1002",
            "1002",
            "1003",
            "1008"
      ],
      "Maximum-Reproduction-Ratio": {
            "0.15x": [
                  "1002"
            ],
            "1/4.6x": [
                  "1005"
            ]
      },
      "Minimum-Focusing-Distance": {
            "0.45-m": [
                  "1002"
            ],
            "0.38-m": [
                  "1005"
            ],
            "0.49-m": [
                  "1006"
            ]
      },
      "Minimum-f/stop": {
            "16": [
                  "1002"
            ],
            "22": [
                  "1005"
            ]
      },
      "Prime": [
            "1002",
            "1002",
            "1003",
            "1007",
            "1008"
      ],
      "Journalism": [
            "1002"
      ],
      "Diameter": {
            "69.2-mm": [
                  "1003"
            ],
            "80.4-mm": [
                  "1007"
            ],
            "74.4-mm": [
                  "1009"
            ]
      },
      "STM": [
            "1003"
      ],
      "Length": {
            "39.3-mm": [
                  "1003"
            ],
            "89.2-mm": [
                  "1007"
            ],
            "96-mm": [
                  "1009"
            ]
      },
      "EF": [
            "1003",
            "1010"
      ],
      "Angle-of-View": {
            "76-Degree---11-Degree30": [
                  "1004"
            ],
            "75\u00c2\u00b0---8\u00c2\u00b0": [
                  "1006"
            ]
      },
      "Wide-angle": [
            "1004",
            "1005",
            "1006",
            "1010"
      ],
      "DX": [
            "1005"
      ],
      "Tamron": [
            "1006",
            "1007",
            "1008",
            "1009"
      ],
      "Macro": [
            "1006"
      ],
      "Zoom,-Macro": [
            "1006"
      ],
      "USD": [
            "1007"
      ],
      "Auto-Focus": [
            "1007",
            "1009"
      ],
      "Image-Stabilisation": {
            "Yes": [
                  "1007",
                  "1009"
            ]
      },
      "Full-Frame": [
            "1007",
            "1009"
      ],
      "Nikon-Mount": [
            "1007"
      ],
      "Class-Close-Focusing": [
            "1007"
      ],
      "Pack-of": {
            "1": [
                  "1007",
                  "1009"
            ]
      },
      "Wedding-&-Events": [
            "1007"
      ],
      "Water-Resistant": {
            "Yes": [
                  "1007",
                  "1009"
            ],
            "No": [
                  "1008"
            ]
      },
      "Portrait": [
            "1008"
      ],
      "Fix": [
            "1008"
      ],
      "PZD": [
            "1009"
      ],
      "Rotation": [
            "1009"
      ],
      "Ring-type-USM": [
            "1010"
      ],
      "Auto": [
            "1010"
      ],
      "Ultra-Wide-Angle": [
            "1010"
      ],
      "Art": [
            "1010"
      ]
}